logngo/__init__.py
logngo/handler.py
logngo/main.py
logngo/singleton.py
logngo/socket.py
logngo/utils.py
logtc/__init__.py
logtc/handler.py
logtc/logger.py
logtc/singleton.py
logtc/socket.py
logtc/utils.py
logngo-1.7.36.dist-info/METADATA
logngo-1.7.36.dist-info/WHEEL
logngo-1.7.36.dist-info/top_level.txt
logngo-1.7.36.dist-info/RECORD
