Metadata-Version: 2.1
Name: logngo
Version: 1.7.36
Summary: Log chains for webserver
Home-page: https://github.com/hoangtc125/logtc
Author: Cong Hoang Tran
Author-email: trconghoangg@gmail.com
Classifier: Programming Language :: Python :: 3
Classifier: License :: OSI Approved :: MIT License
Classifier: Operating System :: OS Independent
Requires-Python: >=3.6
Requires-Dist: requests
Requires-Dist: contextvars
Requires-Dist: websocket-client
Requires-Dist: websockets
Requires-Dist: python-socketio <5.0,>=4.0
Requires-Dist: python-engineio <4.0,>=3.0
